README.txt
setup.py
lca_metrics/__init__.py
lca_metrics/metrics.py
lca_metrics/test.py
lca_metrics.egg-info/PKG-INFO
lca_metrics.egg-info/SOURCES.txt
lca_metrics.egg-info/dependency_links.txt
lca_metrics.egg-info/requires.txt
lca_metrics.egg-info/top_level.txt