Metadata-Version: 1.1
Name: lca-metrics
Version: 0.1.0
Summary: UNKNOWN
Home-page: UNKNOWN
Author: Shinya SUZUKI
Author-email: shinya.s.825@gmail.com
License: MIT
Keywords: validation,metrics,machine learning
Platform: UNKNOWN
Classifier: Programming Language :: Python
Classifier: Programming Language :: Python :: 3
Classifier: License :: OSI Approved :: MIT License
Classifier: Topic :: Scientific/Engineering :: Information Analysis
